quart_github_webhook/__init__.py
quart_github_webhook/webhook.py
quart_github_webhook-0.2.dev1.dist-info/LICENSE
quart_github_webhook-0.2.dev1.dist-info/METADATA
quart_github_webhook-0.2.dev1.dist-info/WHEEL
quart_github_webhook-0.2.dev1.dist-info/top_level.txt
quart_github_webhook-0.2.dev1.dist-info/RECORD
